<?xml version="1.0" encoding="UTF-8"?>
<DOCUMENT><P><W> बाहरी </W><W> दिल्ली </W><W> के </W><W> बवाना </W><W> औद्योगिक </W><W> क्षेत्र </W><W> के </W><W> सेक्टर </W><W> पांच </W><W> की </W><W> एक </W><W> पटाखा </W><W> फैक्टरी </W><W> में </W><W> शनिवार </W><W> शाम </W><W> लगी </W><W> भीषण </W><W> आग </W><W> में </W><W> 17 </W><W> लोगों </W><W> की </W><W> मौत </W><W> हो </W><W> गई </W><W> और </W><W> तीन </W><W> लोग </W><W> बुरी </W><W> तरह </W><W> से </W><W> झुलस </W><EMOTION1-SENTENCE TYPE="SADNESS"><EMOTION2-SENTENCE TYPE="SYMPATHY/PENSIVENESS"><EMOTION1-INTENSITY-SENTENCE TYPE="0.4"><EMOTION2-INTENSITY-SENTENCE TYPE="0.3"><W> गए। </W></EMOTION2-INTENSITY-SENTENCE></EMOTION1-INTENSITY-SENTENCE></EMOTION2-SENTENCE></EMOTION1-SENTENCE><W> मरने </W><W> वालों </W><W> में </W><W> दस </W><W> महिला </W><W> कामगार </W><EMOTION1-SENTENCE TYPE="SADNESS"><EMOTION1-INTENSITY-SENTENCE TYPE="0.3"><W> हैं। शनिवार </W></EMOTION1-INTENSITY-SENTENCE></EMOTION1-SENTENCE><W> को </W><W> बवाना </W><W> औद्योगिक </W><W> इलाके </W><W> के </W><W> ही </W><W> सेक्टर-एक </W><W> और </W><W> सेक्टर-तीन </W><W> में </W><W> भी </W><W> आग </W><W> लगने </W><W> की </W><W> दो </W><W> अलग-अलग </W><W> घटनाएं </W><W> हुईं, </W><W> हालांकि </W><W> यहां </W><W> जानमाल </W><W> के </W><W> नुकसान </W><W> की </W><W> सूचना </W><W> नहीं </W><EMOTION1-SENTENCE TYPE="FEAR/ANXIETY"><EMOTION1-INTENSITY-SENTENCE TYPE="0.2"><W> है। </W></EMOTION1-INTENSITY-SENTENCE></EMOTION1-SENTENCE><W> इन </W><W> फैक्टरियों </W><W> में </W><W> प्लास्टिक </W><W> का </W><W> सामान </W><W> बनता </W><EMOTION1-SENTENCE TYPE="NO-EMOTION"><EMOTION1-INTENSITY-SENTENCE TYPE="0.2"><W> था। सेक्टर-पांच </W></EMOTION1-INTENSITY-SENTENCE></EMOTION1-SENTENCE><W> की </W><W> पटाखा </W><W> फैक्टरी </W><W> में </W><W> लगी </W><W> आग </W><W> सबसे </W><W> भीषण </W><EMOTION1-SENTENCE TYPE="SADNESS"><EMOTION2-SENTENCE TYPE="FEAR/ANXIETY"><EMOTION1-INTENSITY-SENTENCE TYPE="0.4"><EMOTION2-INTENSITY-SENTENCE TYPE="0.2"><W> थी। </W></EMOTION2-INTENSITY-SENTENCE></EMOTION1-INTENSITY-SENTENCE></EMOTION2-SENTENCE></EMOTION1-SENTENCE><W> पुलिस </W><W> ने </W><W> इस </W><W> मामले </W><W> में </W><W> केस </W><W> दर्ज </W><W> कर </W><W> लिया </W><W> है </W><W> और </W><W> आरोपी </W><W> फैक्ट्री </W><W> मालिक </W><W> मनोज </W><W> जैन </W><W> को </W><W> भी </W><W> गिरफ्तार </W><W> कर </W><W> लिया </W><EMOTION1-SENTENCE TYPE="OPTIMISM"><EMOTION1-INTENSITY-SENTENCE TYPE="0.3"><EMOTION1-PARAGRAPH TYPE="SADNESS"><EMOTION2-PARAGRAPH TYPE="SYMPATHY/PENSIVENESS"><EMOTION1-INTENSITY-PARAGRAPH TYPE="0.4"><EMOTION2-INTENSITY-PARAGRAPH TYPE="0.3"><W> है। </W></EMOTION2-INTENSITY-PARAGRAPH></EMOTION1-INTENSITY-PARAGRAPH></EMOTION2-PARAGRAPH></EMOTION1-PARAGRAPH></EMOTION1-INTENSITY-SENTENCE></EMOTION1-SENTENCE></P><P><W> आग </W><W> इतनी </W><W> भयावह </W><W> थी </W><W> कि </W><W> घंटे </W><W> भर </W><W> के </W><W> अंदर </W><W> ही </W><W> फैक्टरी </W><W> के </W><W> बेसमेंट, </W><W> भूतल </W><W> और </W><W> पहली </W><W> मंजिल </W><W> में </W><W> अफरातफरी </W><W> मच </W><EMOTION1-SENTENCE TYPE="FEAR/ANXIETY"><EMOTION2-SENTENCE TYPE="SADNESS"><EMOTION1-INTENSITY-SENTENCE TYPE="0.4"><EMOTION2-INTENSITY-SENTENCE TYPE="0.3"><W> गई। </W></EMOTION2-INTENSITY-SENTENCE></EMOTION1-INTENSITY-SENTENCE></EMOTION2-SENTENCE></EMOTION1-SENTENCE><W> आग </W><W> ने </W><W> इस </W><W> तीन </W><W> मंजिला </W><W> बिल्डिंग </W><W> को </W><W> देखते </W><W> ही </W><W> देखते </W><W> अपनी </W><W> चपेट </W><W> में </W><W> ले </W><EMOTION1-SENTENCE TYPE="FEAR/ANXIETY"><EMOTION2-SENTENCE TYPE="SADNESS"><EMOTION1-INTENSITY-SENTENCE TYPE="0.3"><EMOTION2-INTENSITY-SENTENCE TYPE="0.2"><W> लिया। </W></EMOTION2-INTENSITY-SENTENCE></EMOTION1-INTENSITY-SENTENCE></EMOTION2-SENTENCE></EMOTION1-SENTENCE><W> सूचना </W><W> मिलते </W><W> ही </W><W> दिल्ली </W><W> अग्निशमन </W><W> के </W><W> कर्मचारी, </W><W> पुलिस </W><W> व </W><W> एसडीएम </W><W> मौके </W><W> पर </W><EMOTION1-SENTENCE TYPE="OPTIMISM"><EMOTION1-INTENSITY-SENTENCE TYPE="0.2"><W> पहुंचे। रोहिणी </W></EMOTION1-INTENSITY-SENTENCE></EMOTION1-SENTENCE><W> जिले </W><W> के </W><W> पुलिस </W><W> उपायुक्त </W><W> रजनीश </W><W> गुप्ता </W><W> का </W><W> कहना </W><W> है </W><W> कि </W><W> शव </W><W> इतनी </W><W> बुरी </W><W> तरह </W><W> से </W><W> झुलसे </W><W> हुए </W><W> हैं </W><W> कि </W><W> इनकी </W><W> पहचान </W><W> करने </W><W> में </W><W> दिक्कत </W><W> हो </W><W> रही </W><EMOTION1-SENTENCE TYPE="SADNESS"><EMOTION2-SENTENCE TYPE="SYMPATHY/PENSIVENESS"><EMOTION1-INTENSITY-SENTENCE TYPE="0.4"><EMOTION2-INTENSITY-SENTENCE TYPE="0.4"><W> है। </W></EMOTION2-INTENSITY-SENTENCE></EMOTION1-INTENSITY-SENTENCE></EMOTION2-SENTENCE></EMOTION1-SENTENCE><W> दिल्ली </W><W> के </W><W> उपराज्यपाल </W><W> ने </W><W> घटना </W><W> की </W><W> जांच </W><W> के </W><W> आदेश </W><W> दिए </W><EMOTION1-SENTENCE TYPE="OPTIMISM"><EMOTION1-INTENSITY-SENTENCE TYPE="0.3"><W> हैं। </W></EMOTION1-INTENSITY-SENTENCE></EMOTION1-SENTENCE><W> वहीं </W><W> मुख्यमंत्री </W><W> अरविंद </W><W> केजरीवाल </W><W> ने </W><W> संबंधित </W><W> अधिकारियों </W><W> और </W><W> स्थानीय </W><W> जनप्रतिनिधियों </W><W> को </W><W> बचाव </W><W> व </W><W> राहत </W><W> कार्य </W><W> के </W><W> निर्देश </W><EMOTION1-SENTENCE TYPE="OPTIMISM"><EMOTION1-INTENSITY-SENTENCE TYPE="0.3"><W> दिए। </W></EMOTION1-INTENSITY-SENTENCE></EMOTION1-SENTENCE></P><P><W> दिल्ली </W><W> सरकार </W><W> ने </W><W> मृतकों </W><W> के </W><W> परिवार </W><W> को </W><W> 5-5 </W><W> लाख </W><W> रुपए </W><W> और </W><W> घायलों </W><W> को </W><W> 1-1 </W><W> लाख </W><W> रुपए </W><W> का </W><W> मुआवजा </W><W> देने </W><W> की </W><W> घोषणा </W><W> की </W><EMOTION1-SENTENCE TYPE="SYMPATHY/PENSIVENESS"><EMOTION1-INTENSITY-SENTENCE TYPE="0.3"><W> है।घटना </W></EMOTION1-INTENSITY-SENTENCE></EMOTION1-SENTENCE><W> की </W><W> खबर </W><W> मिलते </W><W> ही </W><W> उत्तरी </W><W> दिल्ली </W><W> की </W><W> मेयर </W><W> प्रीति </W><W> अग्रवाल </W><W> भी </W><W> मौके </W><W> पर </W><W> पहुंच </W><W> गई </W><EMOTION1-SENTENCE TYPE="OPTIMISM"><EMOTION1-INTENSITY-SENTENCE TYPE="0.2"><W> थीं। </W></EMOTION1-INTENSITY-SENTENCE></EMOTION1-SENTENCE><W> प्रधानमंत्री </W><W> नरेंद्र </W><W> मोदी </W><W> ने </W><W> भी </W><W> घटना </W><W> पर </W><W> शोक </W><W> जताया </W><EMOTION1-SENTENCE TYPE="SYMPATHY/PENSIVENESS"><EMOTION1-INTENSITY-SENTENCE TYPE="0.3"><W> है। </W></EMOTION1-INTENSITY-SENTENCE></EMOTION1-SENTENCE><W> उन्होंने </W><W> ट्वीट </W><W> कर </W><W> कहा, </W><W> ‘बवाना </W><W> में </W><W> आग </W><W> की </W><W> घटना </W><W> सुनकर </W><W> बहुत </W><W> दुख </W><EMOTION1-SENTENCE TYPE="SYMPATHY/PENSIVENESS"><EMOTION1-INTENSITY-SENTENCE TYPE="0.3"><W> हुआ। </W></EMOTION1-INTENSITY-SENTENCE></EMOTION1-SENTENCE><W> मृतकों </W><W> के </W><W> परिवारों </W><W> के </W><W> साथ </W><W> मेरी </W><W> संवेदनाएं </W><EMOTION1-SENTENCE TYPE="SYMPATHY/PENSIVENESS"><EMOTION1-INTENSITY-SENTENCE TYPE="0.3"><W> हैं। </W></EMOTION1-INTENSITY-SENTENCE></EMOTION1-SENTENCE><W> जो </W><W> इस </W><W> हादसे </W><W> में </W><W> घायल </W><W> हुए </W><W> हैं, </W><W> मैं </W><W> उनके </W><W> जल्द </W><W> ठीक </W><W> होने </W><W> की </W><W> कामना </W><W> करता </W><EMOTION1-SENTENCE TYPE="SYMPATHY/PENSIVENESS"><EMOTION1-INTENSITY-SENTENCE TYPE="0.3"><EMOTION1-PARAGRAPH TYPE="SYMPATHY/PENSIVENESS"><EMOTION2-PARAGRAPH TYPE="SADNESS"><EMOTION1-INTENSITY-PARAGRAPH TYPE="0.3"><EMOTION2-INTENSITY-PARAGRAPH TYPE="0.3"><W> हूं।’ </W></EMOTION2-INTENSITY-PARAGRAPH></EMOTION1-INTENSITY-PARAGRAPH></EMOTION2-PARAGRAPH></EMOTION1-PARAGRAPH></EMOTION1-INTENSITY-SENTENCE></EMOTION1-SENTENCE></P><P><W> दिल्ली </W><W> अग्निशमन </W><W> विभाग </W><W> और </W><W> पुलिस </W><W> उपायुक्त </W><W> के </W><W> मुताबिक </W><W> शनिवार </W><W> शाम </W><W> 6:20 </W><W> बजे </W><W> सूचना </W><W> मिली </W><W> कि </W><W> एक </W><W> पटाखा </W><W> फैक्टरी </W><W> में </W><W> आग </W><W> लग </W><W> गई </W><EMOTION1-SENTENCE TYPE="SADNESS"><EMOTION1-INTENSITY-SENTENCE TYPE="0.4"><W> है। </W></EMOTION1-INTENSITY-SENTENCE></EMOTION1-SENTENCE><W> बीस </W><W> दमकलों </W><W> को </W><W> मौके </W><W> पर </W><W> भेजा </W><EMOTION1-SENTENCE TYPE="OPTIMISM"><EMOTION1-INTENSITY-SENTENCE TYPE="0.3"><W> गया। </W></EMOTION1-INTENSITY-SENTENCE></EMOTION1-SENTENCE><W> उपायुक्त </W><W> के </W><W> मुताबिक </W><W> सेक्टर-पांच </W><W> में </W><W> एफ-83 </W><W> की </W><W> जिस </W><W> पटाखा </W><W> फैक्टरी </W><W> में </W><W> आग </W><W> लगी </W><W> वहां </W><W> हालात </W><W> भयावह </W><EMOTION1-SENTENCE TYPE="FEAR/ANXIETY"><EMOTION2-SENTENCE TYPE="SADNESS"><EMOTION1-INTENSITY-SENTENCE TYPE="0.4"><EMOTION2-INTENSITY-SENTENCE TYPE="0.3"><W> थे। </W></EMOTION2-INTENSITY-SENTENCE></EMOTION1-INTENSITY-SENTENCE></EMOTION2-SENTENCE></EMOTION1-SENTENCE><W> फैक्टरी </W><W> में </W><W> काम </W><W> करने </W><W> वाले </W><W> मजदूरों </W><W> में </W><W> अफरातफरी </W><W> मच </W><EMOTION1-SENTENCE TYPE="FEAR/ANXIETY"><EMOTION2-SENTENCE TYPE="SADNESS"><EMOTION1-INTENSITY-SENTENCE TYPE="0.3"><EMOTION2-INTENSITY-SENTENCE TYPE="0.2"><W> गई। </W></EMOTION2-INTENSITY-SENTENCE></EMOTION1-INTENSITY-SENTENCE></EMOTION2-SENTENCE></EMOTION1-SENTENCE><W> हादसे </W><W> में </W><W> 17 </W><W> मजदूरों </W><W> की </W><W> मौत </W><W> हो </W><W> गई </W><W> जबकि </W><W> तीन </W><W> की </W><W> हालत </W><W> अस्पताल </W><W> में </W><W> डाक्टरों </W><W> ने </W><W> नाजुक </W><EMOTION1-SENTENCE TYPE="SADNESS"><EMOTION2-SENTENCE TYPE="SYMPATHY/PENSIVENESS"><EMOTION1-INTENSITY-SENTENCE TYPE="0.3"><EMOTION2-INTENSITY-SENTENCE TYPE="0.4"><W> बताई। </W></EMOTION2-INTENSITY-SENTENCE></EMOTION1-INTENSITY-SENTENCE></EMOTION2-SENTENCE></EMOTION1-SENTENCE><W> जिन </W><W> महिला </W><W> मजदूरों </W><W> की </W><W> मौत </W><W> हुई </W><W> है </W><W> उनमें </W><W> कुछ </W><W> नाबालिग </W><W> भी </W><W> बताई </W><W> जा </W><W> रही </W><EMOTION1-SENTENCE TYPE="SYMPATHY/PENSIVENESS"><EMOTION2-SENTENCE TYPE="SADNESS"><EMOTION1-INTENSITY-SENTENCE TYPE="0.3"><EMOTION2-INTENSITY-SENTENCE TYPE="0.4"><W> हैं। </W></EMOTION2-INTENSITY-SENTENCE></EMOTION1-INTENSITY-SENTENCE></EMOTION2-SENTENCE></EMOTION1-SENTENCE><W> उन्होंने </W><W> बताया </W><W> कि </W><W> जिस </W><W> वक्त </W><W> फैक्टरी </W><W> में </W><W> आग </W><W> लगी </W><W> थी </W><W> उस </W><W> समय </W><W> वहां </W><W> करीब </W><W> 50 </W><W> कर्मचारी </W><W> काम </W><W> कर </W><W> रहे </W><EMOTION1-SENTENCE TYPE="SADNESS"><EMOTION1-INTENSITY-SENTENCE TYPE="0.2"><EMOTION1-PARAGRAPH TYPE="SYMPATHY/PENSIVENESS"><EMOTION2-PARAGRAPH TYPE="SADNESS"><EMOTION1-INTENSITY-PARAGRAPH TYPE="0.4"><EMOTION2-INTENSITY-PARAGRAPH TYPE="0.3"><W> थे। </W></EMOTION2-INTENSITY-PARAGRAPH></EMOTION1-INTENSITY-PARAGRAPH></EMOTION2-PARAGRAPH></EMOTION1-PARAGRAPH></EMOTION1-INTENSITY-SENTENCE></EMOTION1-SENTENCE></P><P><W> आग </W><W> लगने </W><W> के </W><W> कारणों </W><W> का </W><W> पता </W><W> नहीं </W><W> चल </W><W> सका </W><EMOTION1-SENTENCE TYPE="DISGUST"><EMOTION1-INTENSITY-SENTENCE TYPE="0.3"><W> है। </W></EMOTION1-INTENSITY-SENTENCE></EMOTION1-SENTENCE><W> कुछ </W><W> लोग </W><W> आग </W><W> लगने </W><W> पर </W><W> जान </W><W> बचाने </W><W> के </W><W> लिए </W><W> फैक्टरी </W><W> की </W><W> तीसरी </W><W> मंजिल </W><W> से </W><W> नीचे </W><W> कूद </W><W> गए </W><W> और </W><W> चोटिल </W><W> हो </W><EMOTION1-SENTENCE TYPE="SYMPATHY/PENSIVENESS"><EMOTION1-INTENSITY-SENTENCE TYPE="0.4"><W> गए। </W></EMOTION1-INTENSITY-SENTENCE></EMOTION1-SENTENCE><W> दिल्ली </W><W> पुलिस </W><W> और </W><W> दिल्ली </W><W> अग्निशमन </W><W> के </W><W> कर्मियों </W><W> ने </W><W> झुलसे </W><W> लोगों </W><W> को </W><W> एंबुलेस </W><W> की </W><W> मदद </W><W> से </W><W> महर्षि </W><W> बाल्मीकि </W><W> अस्पताल </W><W> में </W><W> भर्ती </W><EMOTION1-SENTENCE TYPE="OPTIMISM"><EMOTION1-INTENSITY-SENTENCE TYPE="0.3"><W> कराया। </W></EMOTION1-INTENSITY-SENTENCE></EMOTION1-SENTENCE><W> पुलिस </W><W> उपायुक्त </W><W> ने </W><W> बताया </W><W> कि </W><W> मरने </W><W> वालों </W><W> की </W><W> संख्या </W><W> बढ़ </W><W> सकती </W><EMOTION1-SENTENCE TYPE="SADNESS"><EMOTION2-SENTENCE TYPE="FEAR/ANXIETY"><EMOTION1-INTENSITY-SENTENCE TYPE="0.4"><EMOTION2-INTENSITY-SENTENCE TYPE="0.2"><W> है। </W></EMOTION2-INTENSITY-SENTENCE></EMOTION1-INTENSITY-SENTENCE></EMOTION2-SENTENCE></EMOTION1-SENTENCE><W> आग </W><W> इतनी </W><W> तेजी </W><W> से </W><W> फैली </W><W> कि </W><W> किसी </W><W> को </W><W> बाहर </W><W> निकलने </W><W> का </W><W> मौका </W><W> ही </W><W> नहीं </W><EMOTION1-SENTENCE TYPE="SADNESS"><EMOTION2-SENTENCE TYPE="SYMPATHY/PENSIVENESS"><EMOTION3-SENTENCE TYPE="FEAR/ANXIETY"><EMOTION1-INTENSITY-SENTENCE TYPE="0.4"><EMOTION2-INTENSITY-SENTENCE TYPE="0.3"><EMOTION3-INTENSITY-SENTENCE TYPE="0.2"><EMOTION1-PARAGRAPH TYPE="SADNESS"><EMOTION2-PARAGRAPH TYPE="SYMPATHY/PENSIVENESS"><EMOTION1-INTENSITY-PARAGRAPH TYPE="0.4"><EMOTION2-INTENSITY-PARAGRAPH TYPE="0.3"><W> मिला। </W></EMOTION2-INTENSITY-PARAGRAPH></EMOTION1-INTENSITY-PARAGRAPH></EMOTION2-PARAGRAPH></EMOTION1-PARAGRAPH></EMOTION3-INTENSITY-SENTENCE></EMOTION2-INTENSITY-SENTENCE></EMOTION1-INTENSITY-SENTENCE></EMOTION3-SENTENCE></EMOTION2-SENTENCE></EMOTION1-SENTENCE></P><P><W> दिल्ली </W><W> अग्निशमन </W><W> की </W><W> 30 </W><W> गाड़ियां </W><W> देर </W><W> रात </W><W> तक </W><W> आग </W><W> बुझाने </W><W> में </W><W> लगी </W><EMOTION1-SENTENCE TYPE="OPTIMISM"><EMOTION1-INTENSITY-SENTENCE TYPE="0.2"><W> रहीं। </W></EMOTION1-INTENSITY-SENTENCE></EMOTION1-SENTENCE><W> शवों </W><W> को </W><W> पोस्टमार्टम </W><W> के </W><W> लिए </W><W> रोहिणी </W><W> के </W><W> आंबेडकर </W><W> अस्पताल </W><W> भेजा </W><EMOTION1-SENTENCE TYPE="SYMPATHY/PENSIVENESS"><EMOTION2-SENTENCE TYPE="SADNESS"><EMOTION1-INTENSITY-SENTENCE TYPE="0.3"><EMOTION2-INTENSITY-SENTENCE TYPE="0.2"><W> गया। </W></EMOTION2-INTENSITY-SENTENCE></EMOTION1-INTENSITY-SENTENCE></EMOTION2-SENTENCE></EMOTION1-SENTENCE><W> पहचान </W><W> के </W><W> लिए </W><W> मृतकों </W><W> के </W><W> परिजनों </W><W> को </W><W> बुलाया </W><W> गया </W><EMOTION1-SENTENCE TYPE="SYMPATHY/PENSIVENESS"><EMOTION1-INTENSITY-SENTENCE TYPE="0.3"><W> है। </W></EMOTION1-INTENSITY-SENTENCE></EMOTION1-SENTENCE><W> फैक्टरी </W><W> मालिक </W><W> फरार </W><W> बताया </W><W> गया </W><EMOTION1-SENTENCE TYPE="DISGUST"><EMOTION1-INTENSITY-SENTENCE TYPE="0.3"><W> है। </W></EMOTION1-INTENSITY-SENTENCE></EMOTION1-SENTENCE><W> उसे </W><W> पकड़ने </W><W> की </W><W> कोशिश </W><W> की </W><W> जा </W><W> रही </W><EMOTION1-SENTENCE TYPE="OPTIMISM"><EMOTION1-INTENSITY-SENTENCE TYPE="0.2"><W> है। </W></EMOTION1-INTENSITY-SENTENCE></EMOTION1-SENTENCE><W> फैक्टरी </W><W> मालिक </W><W> के </W><W> पास </W><W> लाइसेंस </W><W> था </W><W> या </W><W> नहीं, </W><W> यह </W><W> जांच </W><W> भी </W><W> की </W><W> जा </W><W> रही </W><EMOTION1-SENTENCE TYPE="SYMPATHY/PENSIVENESS"><EMOTION1-INTENSITY-SENTENCE TYPE="0.3"><W> है। </W></EMOTION1-INTENSITY-SENTENCE></EMOTION1-SENTENCE><W> शुरुआती </W><W> जांच </W><W> में </W><W> शार्ट </W><W> सर्किट </W><W> से </W><W> आग </W><W> लगने </W><W> की </W><W> बात </W><W> कही </W><W> जा </W><W> रही </W><W> है </W><W> जबकि </W><W> स्थानीय </W><W> लोगों </W><W> का </W><W> कहना </W><W> है </W><W> कि </W><W> पटाखों </W><W> की </W><W> वजह </W><W> से </W><W> आग </W><EMOTION1-SENTENCE TYPE="SADNESS"><EMOTION1-INTENSITY-SENTENCE TYPE="0.3"><EMOTION1-PARAGRAPH TYPE="SYMPATHY/PENSIVENESS"><EMOTION2-PARAGRAPH TYPE="SADNESS"><EMOTION1-INTENSITY-PARAGRAPH TYPE="0.4"><EMOTION2-INTENSITY-PARAGRAPH TYPE="0.2"><W> लगी। </W></EMOTION2-INTENSITY-PARAGRAPH></EMOTION1-INTENSITY-PARAGRAPH></EMOTION2-PARAGRAPH></EMOTION1-PARAGRAPH></EMOTION1-INTENSITY-SENTENCE></EMOTION1-SENTENCE></P></DOCUMENT>